CQukuaiLianBiancheng/README.md
CQukuaiLianBiancheng/__init__.py
CQukuaiLianBiancheng/__main__.py
CQukuaiLianBiancheng/file.epub
CQukuaiLianBiancheng/index.html
CQukuaiLianBiancheng/css/__init__.py
CQukuaiLianBiancheng/css/annotations.css
CQukuaiLianBiancheng/css/main.css
CQukuaiLianBiancheng/css/normalize.css
CQukuaiLianBiancheng/css/popup.css
CQukuaiLianBiancheng/font/__init__.py
CQukuaiLianBiancheng/font/fontello.eot
CQukuaiLianBiancheng/font/fontello.svg
CQukuaiLianBiancheng/font/fontello.ttf
CQukuaiLianBiancheng/font/fontello.woff
CQukuaiLianBiancheng/img/__init__.py
CQukuaiLianBiancheng/img/annotator-glyph-sprite.png
CQukuaiLianBiancheng/img/annotator-icon-sprite.png
CQukuaiLianBiancheng/img/apple-touch-icon.png
CQukuaiLianBiancheng/img/cancelfullscreen.png
CQukuaiLianBiancheng/img/close.png
CQukuaiLianBiancheng/img/fullscreen.png
CQukuaiLianBiancheng/img/loader.gif
CQukuaiLianBiancheng/img/menu-icon.png
CQukuaiLianBiancheng/img/save.png
CQukuaiLianBiancheng/img/saved.png
CQukuaiLianBiancheng/img/settings-s.png
CQukuaiLianBiancheng/img/settings.png
CQukuaiLianBiancheng/img/star.png
CQukuaiLianBiancheng/js/__init__.py
CQukuaiLianBiancheng/js/epub.js
CQukuaiLianBiancheng/js/epub.min.js
CQukuaiLianBiancheng/js/epub.min.map
CQukuaiLianBiancheng/js/hooks.min.js
CQukuaiLianBiancheng/js/hooks.min.map
CQukuaiLianBiancheng/js/reader.js
CQukuaiLianBiancheng/js/reader.js.map
CQukuaiLianBiancheng/js/reader.min.js
CQukuaiLianBiancheng/js/reader.min.map
CQukuaiLianBiancheng/js/hooks/__init__.py
CQukuaiLianBiancheng/js/hooks/extensions/__init__.py
CQukuaiLianBiancheng/js/hooks/extensions/highlight.js
CQukuaiLianBiancheng/js/libs/__init__.py
CQukuaiLianBiancheng/js/libs/jquery.min.js
CQukuaiLianBiancheng/js/libs/localforage.min.js
CQukuaiLianBiancheng/js/libs/screenfull.js
CQukuaiLianBiancheng/js/libs/screenfull.min.js
CQukuaiLianBiancheng/js/libs/zip.min.js
CQukuaiLianBiancheng/js/plugins/__init__.py
CQukuaiLianBiancheng/js/plugins/hypothesis.js
c_qukuai_lian_biancheng-2024.3.4.0.dist-info/METADATA
c_qukuai_lian_biancheng-2024.3.4.0.dist-info/WHEEL
c_qukuai_lian_biancheng-2024.3.4.0.dist-info/entry_points.txt
c_qukuai_lian_biancheng-2024.3.4.0.dist-info/top_level.txt
c_qukuai_lian_biancheng-2024.3.4.0.dist-info/RECORD
